admin_edit_lock/__init__.py
admin_edit_lock/admin.py
admin_edit_lock/static/admin_edit_lock/update_lock.js
django_admin_edit_lock-0.4.0.dist-info/WHEEL
django_admin_edit_lock-0.4.0.dist-info/METADATA
django_admin_edit_lock-0.4.0.dist-info/RECORD
