Metadata-Version: 2.1
Name: django-admin-edit-lock
Version: 0.4.0
Summary: django-admin-edit-lock is a Django application used in admin to prevent simultaneous edit by more than one users.
Home-page: https://github.com/demestav/django-admin-edit-lock
License: MIT
Author: Demetris Stavrou
Requires-Python: >=3.8,<4.0
Classifier: License :: OSI Approved :: MIT License
Classifier: Programming Language :: Python :: 3
Classifier: Programming Language :: Python :: 3.8
Classifier: Programming Language :: Python :: 3.9
Requires-Dist: Django (>=2.2)
